clc_by_ksdev/__init__.py
clc_by_ksdev/core.py
clc_by_ksdev/interpreter.py
clc_by_ksdev-0.1.1.dist-info/METADATA
clc_by_ksdev-0.1.1.dist-info/WHEEL
clc_by_ksdev-0.1.1.dist-info/top_level.txt
clc_by_ksdev-0.1.1.dist-info/RECORD
