Metadata-Version: 2.4
Name: clc_by_ksdev
Version: 0.1.1
Summary: CALC+ language interpreter
Author-email: KsDev <contatoksdev@tutamail.com>
License: MIT
Requires-Python: >=3.8
